dictpath/__init__.py
dictpath/accessors.py
dictpath/parsers.py
dictpath/paths.py
dictpath-0.1.3.dist-info/LICENSE
dictpath-0.1.3.dist-info/METADATA
dictpath-0.1.3.dist-info/WHEEL
dictpath-0.1.3.dist-info/top_level.txt
dictpath-0.1.3.dist-info/RECORD
